pyyts
